qa_pytest_rest/__init__.py
qa_pytest_rest/rest_configuration.py
qa_pytest_rest/rest_steps.py
qa_pytest_rest/rest_tests.py
qa_pytest_rest-0.1.1.dist-info/METADATA
qa_pytest_rest-0.1.1.dist-info/WHEEL
qa_pytest_rest-0.1.1.dist-info/RECORD
